pysampling/__init__.py
pysampling/_version.py
pysampling/constant.py
pysampling/state.py
pysampling/colvars/__init__.py
pysampling/colvars/alanine.py
pysampling/colvars/base.py
pysampling/colvars/bond.py
pysampling/colvars/build.py
pysampling/colvars/dz.py
pysampling/colvars/formate.py
pysampling/colvars/plumed.py
pysampling/colvars/tensorflow.py
pysampling/colvars/toy2d.py
pysampling/engines/__init__.py
pysampling/engines/ase_calculator.py
pysampling/engines/build.py
pysampling/engines/cp2k.py
pysampling/engines/engine.py
pysampling/engines/lammps.py
pysampling/engines/toy.py
pysampling/sampling_routines/__init__.py
pysampling/sampling_routines/ams.py
pysampling/sampling_routines/committor.py
pysampling/sampling_routines/ffs.py
pysampling/sampling_routines/plain.py
pysampling/sampling_routines/sampling.py
pysampling/sampling_routines/tps.py
pysampling/scripts/__init__.py
pysampling/scripts/run.py
pysampling/trajectories/__init__.py
pysampling/trajectories/trajectories.py
pysampling/trajectories/trajectory.py
mir_pysampling-0.0.3.dist-info/METADATA
mir_pysampling-0.0.3.dist-info/WHEEL
mir_pysampling-0.0.3.dist-info/entry_points.txt
mir_pysampling-0.0.3.dist-info/top_level.txt
mir_pysampling-0.0.3.dist-info/zip-safe
mir_pysampling-0.0.3.dist-info/RECORD
