Metadata-Version: 2.1
Name: mir-pysampling
Version: 0.0.3
Summary: UNKNOWN
Home-page: UNKNOWN
Author: Lixin Sun
License: UNKNOWN
Platform: UNKNOWN
Requires-Python: >=3.6.9
Requires-Dist: numpy
Requires-Dist: matplotlib
Requires-Dist: ase
Requires-Dist: pyfile-utils
Requires-Dist: ndsimulator
